Metadata-Version: 1.1
Name: hurumap
Version: 0.7.8
Summary: A Django application for exploring census and other place-specific data
Home-page: https://github.com/CodeForAfrica/HURUmap
Author: Code for Africa
Author-email: support@codeforafrica.org
License: MIT
Platform: UNKNOWN
Classifier: Development Status :: 4 - Beta
Classifier: Intended Audience :: Developers
Classifier: License :: OSI Approved :: MIT License
Classifier: Programming Language :: Python
Classifier: Programming Language :: Python :: 2
Classifier: Programming Language :: Python :: 2.7
